openrouter_exception_handler/__init__.py
openrouter_exception_handler/exception_handler.py
openrouter_exception_handler-0.5.0.dist-info/METADATA
openrouter_exception_handler-0.5.0.dist-info/WHEEL
openrouter_exception_handler-0.5.0.dist-info/top_level.txt
openrouter_exception_handler-0.5.0.dist-info/RECORD
