Metadata-Version: 2.2
Name: openrouter_exception_handler
Version: 0.5.0
Summary: Handler for exceptions in Python with OpenRouter.ai
Author: Dannybombastic
Author-email: Dannybombastic <dannybombastic@example.com>
License: MIT
Project-URL: Homepage, https://github.com/dannybombastic/openrouter_exception_handler
Project-URL: Repository, https://github.com/dannybombastic/openrouter_exception_handler
Keywords: openrouter,exception,handler
Classifier: Development Status :: 4 - Beta
Classifier: Intended Audience :: Developers
Classifier: License :: OSI Approved :: MIT License
Classifier: Programming Language :: Python :: 3
Classifier: Programming Language :: Python :: 3.6
Classifier: Programming Language :: Python :: 3.7
Classifier: Programming Language :: Python :: 3.8
Classifier: Programming Language :: Python :: 3.9
Classifier: Programming Language :: Python :: 3.10
Classifier: Programming Language :: Python :: 3 :: Only
Classifier: Topic :: Software Development :: Libraries
Classifier: Topic :: Software Development :: Libraries :: Python Modules
Classifier: Typing :: Typed
Requires-Python: >=3.6
Requires-Dist: requests
Dynamic: author
Dynamic: requires-python
